django_bolt/__init__.py
django_bolt/_core.abi3.so
django_bolt/_json.py
django_bolt/_kwargs/__init__.py
django_bolt/_kwargs/extractors.py
django_bolt/_kwargs/model.py
django_bolt/_kwargs/runtime.py
django_bolt/admin/__init__.py
django_bolt/admin/admin_detection.py
django_bolt/admin/asgi_bridge.py
django_bolt/admin/routes.py
django_bolt/admin/static.py
django_bolt/admin/static_routes.py
django_bolt/analysis.py
django_bolt/api.py
django_bolt/apps.py
django_bolt/auth/__init__.py
django_bolt/auth/anonymous.py
django_bolt/auth/backends.py
django_bolt/auth/guards.py
django_bolt/auth/jwt_utils.py
django_bolt/auth/revocation.py
django_bolt/auth/token.py
django_bolt/auth/user_loader.py
django_bolt/bootstrap.py
django_bolt/cli.py
django_bolt/concurrency.py
django_bolt/datastructures.py
django_bolt/decorators.py
django_bolt/dependencies.py
django_bolt/enums.py
django_bolt/error_handlers.py
django_bolt/exceptions.py
django_bolt/health.py
django_bolt/logging/__init__.py
django_bolt/logging/config.py
django_bolt/logging/middleware.py
django_bolt/management/__init__.py
django_bolt/management/commands/__init__.py
django_bolt/management/commands/runbolt.py
django_bolt/middleware/__init__.py
django_bolt/middleware/compiler.py
django_bolt/middleware/compression.py
django_bolt/middleware/django_adapter.py
django_bolt/middleware/django_loader.py
django_bolt/middleware/middleware.py
django_bolt/middleware_response.py
django_bolt/openapi/__init__.py
django_bolt/openapi/config.py
django_bolt/openapi/plugins.py
django_bolt/openapi/routes.py
django_bolt/openapi/schema_generator.py
django_bolt/openapi/spec/__init__.py
django_bolt/openapi/spec/base.py
django_bolt/openapi/spec/callback.py
django_bolt/openapi/spec/components.py
django_bolt/openapi/spec/contact.py
django_bolt/openapi/spec/discriminator.py
django_bolt/openapi/spec/encoding.py
django_bolt/openapi/spec/enums.py
django_bolt/openapi/spec/example.py
django_bolt/openapi/spec/external_documentation.py
django_bolt/openapi/spec/header.py
django_bolt-0.5.1.dist-info/METADATA
django_bolt-0.5.1.dist-info/WHEEL
django_bolt-0.5.1.dist-info/entry_points.txt
django_bolt-0.5.1.dist-info/RECORD
