Metadata-Version: 2.4
Name: django-bolt
Version: 0.5.1
Classifier: Development Status :: 3 - Alpha
Classifier: Intended Audience :: Developers
Classifier: License :: OSI Approved :: MIT License
Classifier: Programming Language :: Python :: 3
Classifier: Programming Language :: Python :: 3.12
Classifier: Programming Language :: Python :: 3.13
Classifier: Programming Language :: Python :: Implementation :: CPython
Classifier: Programming Language :: Python :: Implementation :: PyPy
Classifier: Programming Language :: Rust
Classifier: Framework :: Django
Classifier: Framework :: Django :: 4.2
Classifier: Framework :: Django :: 5.0
Classifier: Framework :: Django :: 5.1
Classifier: Topic :: Internet :: WWW/HTTP
Classifier: Topic :: Internet :: WWW/HTTP :: HTTP Servers
Classifier: Topic :: Software Development :: Libraries :: Application Frameworks
Requires-Dist: django>=4.2
Requires-Dist: click>=8.1
Requires-Dist: msgspec>=0.20
Requires-Dist: pyjwt>=2.10.1
Requires-Dist: typing-extensions>=4.5.0
Requires-Dist: pyyaml>=6.0
Requires-Dist: uvloop>=0.22.1 ; sys_platform != 'win32'
Requires-Dist: pyyaml>=6.0 ; extra == 'yaml'
Provides-Extra: yaml
Summary: High-performance API framework for Django with Rust-powered endpoints delivering 60k+ RPS
Keywords: django,api,rust,performance,actix,pyo3,async
Author-email: Farhan <farhanalirazaazeemi@gmail.com>
License: MIT
Requires-Python: >=3.12
Project-URL: Bug Tracker, https://github.com/FarhanAliRaza/django-bolt/issues
Project-URL: Documentation, https://github.com/FarhanAliRaza/django-bolt#readme
Project-URL: Homepage, https://github.com/FarhanAliRaza/django-bolt
Project-URL: Repository, https://github.com/FarhanAliRaza/django-bolt
